manatee/__init__.py
manatee/main.py
manatee/version.py
manatee-0.0.0.data/scripts/manatee
manatee-0.0.0.dist-info/DESCRIPTION.rst
manatee-0.0.0.dist-info/METADATA
manatee-0.0.0.dist-info/RECORD
manatee-0.0.0.dist-info/WHEEL
manatee-0.0.0.dist-info/entry_points.txt
manatee-0.0.0.dist-info/metadata.json
manatee-0.0.0.dist-info/top_level.txt
