Metadata-Version: 2.0
Name: manatee
Version: 0.0.0
Summary: GNU Social server based on async Python 3
Home-page: https://gitlab.com/sashahart/manatee
Author: Sasha Hart
Author-email: s@sashahart.net
License: AGPLv3+
Keywords: gnu social
Platform: UNKNOWN
Classifier: Development Status :: 1 - Planning
Classifier: Intended Audience :: Developers
Classifier: Topic :: Internet
Classifier: Topic :: Communications :: Chat
Classifier: Operating System :: POSIX
Classifier: Programming Language :: Python :: 3 :: Only
Classifier: Programming Language :: Python :: 3.6
Classifier: License :: OSI Approved :: GNU Affero General Public License v3 or later (AGPLv3+)
